Metadata-Version: 1.0
Name: charcheck
Version: 1.0
Summary: Command line tool to compare translated files
Home-page: https://github.com/asmuth444/charcheck
Author: Abhishek Roul
Author-email: asmuth444@gmail.compile
License: UNKNOWN
Platform: UNKNOWN
